{
	"configurations" : 
	[
		{
			"directories" : 
			[
				{
					"build" : ".",
					"jsonFile" : "directory-.-Debug-f5ebdc15457944623624.json",
					"minimumCMakeVersion" : 
					{
						"string" : "3.10"
					},
					"projectIndex" : 0,
					"source" : ".",
					"targetIndexes" : 
					[
						0
					]
				}
			],
			"name" : "Debug",
			"projects" : 
			[
				{
					"directoryIndexes" : 
					[
						0
					],
					"name" : "Project",
					"targetIndexes" : 
					[
						0
					]
				}
			],
			"targets" : 
			[
				{
					"directoryIndex" : 0,
					"id" : "flutter_assemble::@6890427a1f51a3e7e1df",
					"jsonFile" : "target-flutter_assemble-Debug-730fd4ce30e4fc5b3c03.json",
					"name" : "flutter_assemble",
					"projectIndex" : 0
				}
			]
		}
	],
	"kind" : "codemodel",
	"paths" : 
	{
		"build" : "/home/dell/Triptip/TripTip/build",
		"source" : "/home/dell/Triptip/TripTip/linux/flutter"
	},
	"version" : 
	{
		"major" : 2,
		"minor" : 3
	}
}
